setup.cfg
setup.py
piqq/__init__.py
piqq/piqq.py
piqq/receiver.py
piqq.egg-info/PKG-INFO
piqq.egg-info/SOURCES.txt
piqq.egg-info/dependency_links.txt
piqq.egg-info/requires.txt
piqq.egg-info/top_level.txt
piqq/exceptions/__init__.py
piqq/exceptions/connect_exception.py