Metadata-Version: 1.0
Name: piqq
Version: 0.0.10
Summary: PIQQ - The OOP-based add-on for aioamqp library
Home-page: https://git.hellotan.ru/jar3b/piqq
Author: jar3b
Author-email: hellotan@live.ru
License: MIT
Platform: UNKNOWN
